strands_valkey_session_manager/__init__.py
strands_valkey_session_manager/py.typed
strands_valkey_session_manager/valkey_session_manager.py
strands_valkey_session_manager-0.1.0.dist-info/METADATA
strands_valkey_session_manager-0.1.0.dist-info/WHEEL
strands_valkey_session_manager-0.1.0.dist-info/licenses/LICENSE
strands_valkey_session_manager-0.1.0.dist-info/RECORD
