Metadata-Version: 2.4
Name: strands-valkey-session-manager
Version: 0.1.0
Summary: A session manager for Valkey/Redis using Strands
Project-URL: Homepage, https://github.com/jeromevdl/strands-valkey-session-manager
Project-URL: Repository, https://github.com/jeromevdl/strands-valkey-session-manager
Project-URL: Issues, https://github.com/jeromevdl/strands-valkey-session-manager/issues
Author-email: Jerome Van Der Linden <jeromevdl@gmail.com>
License-Expression: MIT
License-File: LICENSE
Classifier: Development Status :: 4 - Beta
Classifier: Intended Audience :: Developers
Classifier: License :: OSI Approved :: MIT License
Classifier: Operating System :: OS Independent
Classifier: Programming Language :: Python :: 3
Classifier: Programming Language :: Python :: 3.10
Classifier: Programming Language :: Python :: 3.11
Classifier: Programming Language :: Python :: 3.12
Classifier: Programming Language :: Python :: 3.13
Requires-Python: >=3.10
Requires-Dist: strands-agents<2.0.0,>=1.0.0
Requires-Dist: valkey<7.0.0,>=6.0.0
